faltwerk/__init__.py
faltwerk/annotation.py
faltwerk/biochem.py
faltwerk/data.py
faltwerk/external.py
faltwerk/geometry.py
faltwerk/io.py
faltwerk/learn.py
faltwerk/models.py
faltwerk/parsers.py
faltwerk/stats.py
faltwerk/utils.py
faltwerk/vis.py
faltwerk/data/ligands/InteracDome_v0.3-confident.tsv
faltwerk/data/ligands/InteracDome_v0.3-representable.tsv
faltwerk/data/ligands/InteracDome_v0.3-representableNR.tsv
faltwerk-0.5.dist-info/METADATA
faltwerk-0.5.dist-info/WHEEL
faltwerk-0.5.dist-info/top_level.txt
faltwerk-0.5.dist-info/RECORD
