Metadata-Version: 2.1
Name: faltwerk
Version: 0.5
Summary: Spatial analysis of protein structures
Author: Adrian Viehweger
Author-email: adrian.viehweger@medizin.uni-leipzig.de
License: BSD 3-clause
Requires-Dist: biopython (==1.79)
Requires-Dist: screed (==1.0.5)
Requires-Dist: py3Dmol (==1.8.1)
Requires-Dist: markov-clustering (==0.0.6.dev0)
Requires-Dist: hdbscan (==0.8.28)
Requires-Dist: networkx (==2.6.3)
Requires-Dist: numpy (==1.21.6)
Requires-Dist: pandas (==1.3.5)
Requires-Dist: matplotlib (==3.5.3)
Requires-Dist: pytest (==7.1.2)
Requires-Dist: libpysal (==4.6.2)
Requires-Dist: esda (==2.4.3)
Requires-Dist: multiprocess (==0.70.13)
Requires-Dist: nbsphinx
Requires-Dist: myst-parser (==0.18.1)
Requires-Dist: Jinja2 (==3.1.2)
Requires-Dist: alabaster
Requires-Dist: ipython
Requires-Dist: sphinxcontrib-napoleon
Requires-Dist: docutils (<0.20,>=0.17.1)
